[
  {
    "x": 548,
    "y": 600,
    "type": "long_dirt"
  },
  {
    "x": 744,
    "y": 600,
    "type": "long_dirt"
  },
  {
    "x": 0,
    "y": 550,
    "type": "long_dirt"
  },
  {
    "x": 196,
    "y": 550,
    "type": "long_dirt"
  },
  {
    "x": 548,
    "y": 500,
    "type": "long_dirt"
  },
  {
    "x": 744,
    "y": 500,
    "type": "long_dirt"
  },
  {
    "x": 0,
    "y": 450,
    "type": "long_dirt"
  },
  {
    "x": 196,
    "y": 450,
    "type": "long_dirt"
  },
  {
    "x": 548,
    "y": 400,
    "type": "long_dirt"
  },
  {
    "x": 744,
    "y": 400,
    "type": "long_dirt"
  },
  {
    "x": 0,
    "y": 350,
    "type": "long_dirt"
  },
  {
    "x": 236,
    "y": 350,
    "type": "long_dirt"
  },
  {
    "x": 520,
    "y": 290,
    "type": "long_dirt"
  },
  {
    "x": 520,
    "y": 274,
    "type": "dirt"
  },
  {
    "x": 760,
    "y": 274,
    "type": "dirt"
  },
  {
    "x": 776,
    "y": 258,
    "type": "dirt"
  },
  {
    "x": 792,
    "y": 242,
    "type": "dirt"
  },
  {
    "x": 808,
    "y": 226,
    "type": "dirt"
  },
  {
    "x": 824,
    "y": 210,
    "type": "dirt"
  },
  {
    "x": 840,
    "y": 210,
    "type": "dirt"
  },
  {
    "x": 856,
    "y": 210,
    "type": "dirt"
  }
]